{
    "type": "forge:ore_shaped",
    "pattern": [
        "#  ",
        "EPL",
        " / "
    ],
    "key": {
        "#": {
            "type": "forge:ore_dict",
            "ore": "hammerTool"
        },
        "E": {
            "item": "esperia:pliers",
            "data": 32767
        },
        "P": {
            "item": "esperia:steel_halberd_head"
        },
        "L": {
            "item": "esperia:nails"
        },
        "/": {
            "item": "esperia:pole"
        }
    },
    "result": {
        "item": "esperia:diamond_halberd",
        "count": 1
    }
}